InPostReturnLabel/Code.py
InPostReturnLabel/Label.py
InPostReturnLabel/__about__.py
InPostReturnLabel/__init__.py
InPostReturnLabel/cli/__init__.py
inpostreturnlabel-0.0.2.dist-info/METADATA
inpostreturnlabel-0.0.2.dist-info/WHEEL
inpostreturnlabel-0.0.2.dist-info/entry_points.txt
inpostreturnlabel-0.0.2.dist-info/licenses/LICENSE
inpostreturnlabel-0.0.2.dist-info/RECORD
