Metadata-Version: 2.4
Name: InPostReturnLabel
Version: 0.0.2
Summary: Very simple web-app to generate courier-sized labels with QR code for InPost returns (10-digit codes, usually from Allegro).
Project-URL: Homepage, https://github.com/danielskowronski/InPostReturnLabel
Project-URL: Issues, https://github.com/danielskowronski/InPostReturnLabel/issues
Author: Daniel Skowronski
License-File: LICENSE
Classifier: License :: OSI Approved :: BSD License
Classifier: Operating System :: OS Independent
Classifier: Programming Language :: Python :: 3
Requires-Python: >=3.8
Requires-Dist: click~=8.1.8
Requires-Dist: pillow~=11.2.1
Requires-Dist: segno~=1.6.6
